{
  "title": "Secure Stripe Implementation Checklist",
  "timestamp": "2025-06-15T12:12:25.206Z",
  "security": {
    "authentication": [
      "✅ All payment endpoints require authentication",
      "✅ Return 401 for unauthenticated requests",
      "✅ Clear authentication error messages",
      "✅ No authentication bypass vulnerabilities"
    ],
    "rateLimiting": [
      "✅ Payment endpoints have rate limiting",
      "✅ Rate limits are appropriate (20/hour for payments)",
      "✅ Rate limit errors are user-friendly",
      "✅ Rate limiting prevents abuse"
    ],
    "inputValidation": [
      "✅ All inputs are validated",
      "✅ Validation errors are clear",
      "✅ No injection vulnerabilities",
      "✅ Proper data type checking"
    ],
    "errorHandling": [
      "✅ No sensitive information in errors",
      "✅ Consistent error response format",
      "✅ Proper HTTP status codes",
      "✅ Security events are logged"
    ],
    "webhooks": [
      "✅ Webhook signature validation",
      "✅ Proper webhook error handling",
      "✅ No configuration exposure",
      "✅ Webhook security logging"
    ]
  },
  "userExperience": {
    "errorMessages": [
      "✅ Clear, non-technical language",
      "✅ Specific problem description",
      "✅ Actionable guidance provided",
      "✅ Consistent message format"
    ],
    "statusCodes": [
      "✅ 401 for authentication required",
      "✅ 400 for validation errors",
      "✅ 429 for rate limiting",
      "✅ 503 for service unavailable"
    ],
    "guidance": [
      "✅ Clear next steps for users",
      "✅ Contact support when appropriate",
      "✅ Retry guidance for temporary errors",
      "✅ Alternative action suggestions"
    ]
  },
  "production": {
    "monitoring": [
      "✅ Error tracking implemented",
      "✅ Security event logging",
      "✅ Performance monitoring",
      "✅ Alert configuration"
    ],
    "testing": [
      "✅ Automated security tests",
      "✅ Error scenario testing",
      "✅ Rate limiting tests",
      "✅ Integration tests"
    ]
  }
}